wagtail_hljs/__init__.py
wagtail_hljs/blocks.py
wagtail_hljs/settings.py
wagtail_hljs/static/wagtail_hljs/css/wagtail-hljs-block.css
wagtail_hljs/static/wagtail_hljs/css/wagtail-hljs-block.min.css
wagtail_hljs/static/wagtail_hljs/js/wagtailhljsblock.js
wagtail_hljs/templates/wagtail_hljs/code_block.html
wagtail_hljs/templates/wagtail_hljs/code_block_form.html
wagtail_hljs/templates/wagtail_hljs/raw_code.html
wagtail_hljs/templatetags/__init__.py
wagtail_hljs/templatetags/wagtail_hljs_tags.py
wagtail_hljs/wagtail_hooks.py
wagtail_hljs-0.1.3.dist-info/LICENSE
wagtail_hljs-0.1.3.dist-info/METADATA
wagtail_hljs-0.1.3.dist-info/WHEEL
wagtail_hljs-0.1.3.dist-info/RECORD
