Metadata-Version: 2.1
Name: wagtail-hljs
Version: 0.1.3
Summary: StreamField code blocks for the Wagtail CMS with real-time Highlight.js Syntax Highlighting.
License: BSD-3-Clause
Keywords: wagtail,cms,contact,syntax,code,highlighting,highlighter,highlight.js
Author: John Higgins
Author-email: johnmatthiggins@gmail.com
Requires-Python: >=3.11,<4.0
Classifier: Environment :: Web Environment
Classifier: Framework :: Django
Classifier: Framework :: Wagtail
Classifier: Framework :: Wagtail :: 3
Classifier: Framework :: Wagtail :: 4
Classifier: Framework :: Wagtail :: 5
Classifier: Framework :: Wagtail :: 6
Classifier: Intended Audience :: Developers
Classifier: License :: OSI Approved :: BSD License
Classifier: Operating System :: OS Independent
Classifier: Programming Language :: Python :: 3
Classifier: Programming Language :: Python :: 3.11
Classifier: Programming Language :: Python :: 3.12
Classifier: Programming Language :: Python :: 3.10
Classifier: Programming Language :: Python :: 3.8
Classifier: Programming Language :: Python :: 3.9
Classifier: Topic :: Internet :: WWW/HTTP
Classifier: Topic :: Internet :: WWW/HTTP :: Dynamic Content
Requires-Dist: wagtail (>=4)
